AUTHORS
LICENSE
MANIFEST.in
README.rst
setup.py
src/restible_sqlalchemy/__init__.py
src/restible_sqlalchemy/resource.py
src/restible_sqlalchemy/util.py
src/restible_sqlalchemy.egg-info/PKG-INFO
src/restible_sqlalchemy.egg-info/SOURCES.txt
src/restible_sqlalchemy.egg-info/dependency_links.txt
src/restible_sqlalchemy.egg-info/requires.txt
src/restible_sqlalchemy.egg-info/top_level.txt