Metadata-Version: 1.1
Name: restible-sqlalchemy
Version: 0.2
Summary: SQLAlchemy integration for restible library
Home-page: http://github.com/novopl/restible-sqlalchemy
Author: Mateusz 'novo' Klos
Author-email: novopl@gmail.com
License: MIT
Keywords: restible REST restapi rest server SQLAlchemy
Platform: UNKNOWN
Classifier: Development Status :: 4 - Beta
Classifier: Topic :: Utilities
Classifier: Intended Audience :: Developers
Classifier: Programming Language :: Python
Classifier: License :: OSI Approved :: MIT License
